movemeter/__init__.py
movemeter/directories.py
movemeter/embedtk.py
movemeter/heatmap.py
movemeter/movemeter.py
movemeter/roi.py
movemeter/scriptify_emdedtk.py
movemeter/stabilize.py
movemeter/stacks.py
movemeter/tk_heatmap.py
movemeter/tkgui.py
movemeter/version.py
movemeter/cc_backends/__init__.py
movemeter/cc_backends/opencv.py
movemeter/im_backends/__init__.py
movemeter/im_backends/opencv.py
movemeter/im_backends/tifffile.py
movemeter-0.7.2.dist-info/LICENSE
movemeter-0.7.2.dist-info/METADATA
movemeter-0.7.2.dist-info/WHEEL
movemeter-0.7.2.dist-info/top_level.txt
movemeter-0.7.2.dist-info/RECORD
