Metadata-Version: 2.2
Name: movemeter
Version: 0.7.2
Summary: A motion analysis tool
Home-page: https://github.com/musaprog/movemeter
Author: Joni Kemppainen
Author-email: joni.kemppainen@windowslive.com
Classifier: Programming Language :: Python :: 3
Classifier: License :: OSI Approved :: GNU General Public License v3 (GPLv3) 
Classifier: Operating System :: OS Independent
Requires-Python: >=3.6
License-File: LICENSE
Requires-Dist: numpy
Requires-Dist: matplotlib
Requires-Dist: tifffile
Requires-Dist: Pillow
Requires-Dist: ExifRead
Requires-Dist: opencv-python
Requires-Dist: tk-steroids>=0.8.0
Dynamic: author
Dynamic: author-email
Dynamic: classifier
Dynamic: description
Dynamic: description-content-type
Dynamic: home-page
Dynamic: requires-dist
Dynamic: requires-python
Dynamic: summary
